prabhatai/__init__.py
prabhatai/client.py
prabhatai/utils.py
prabhatai-0.1.0.dist-info/licenses/LICENSE
tests/__init__.py
tests/test_client.py
prabhatai-0.1.0.dist-info/METADATA
prabhatai-0.1.0.dist-info/WHEEL
prabhatai-0.1.0.dist-info/top_level.txt
prabhatai-0.1.0.dist-info/RECORD
