Metadata-Version: 2.4
Name: prabhatai
Version: 0.1.0
Summary: Thin wrapper for OpenRouter chat completions API
Author: PrabhatAI
License: MIT License
Requires-Python: >=3.7
License-File: LICENSE
Requires-Dist: requests
Dynamic: license-file
Dynamic: requires-python
